fdpclient/__init__.py
fdpclient/__version__.py
fdpclient/client.py
fdpclient/config.py
fdpclient/operations.py
tests/__init__.py
tests/test_client.py
tests/test_operations.py
tests/data/catalog01.jsonld
tests/data/catalog01.n3
tests/data/catalog01.nt
tests/data/catalog01.rdf
tests/data/catalog01.ttl
tests/data/catalog01_invalid_missingRequired.ttl
tests/data/catalog01_update.ttl
tests/data/fdp.ttl
tests/data/fdp_update.ttl
fairdatapoint_client-0.1.0.dist-info/LICENSE
fairdatapoint_client-0.1.0.dist-info/METADATA
fairdatapoint_client-0.1.0.dist-info/NOTICE
fairdatapoint_client-0.1.0.dist-info/WHEEL
fairdatapoint_client-0.1.0.dist-info/top_level.txt
fairdatapoint_client-0.1.0.dist-info/RECORD
