Metadata-Version: 2.1
Name: fairdatapoint-client
Version: 0.1.0
Summary: FAIR Data Point API client
Home-page: https://github.com/fair-data/fairdatapoint-client
Author: Cunliang Geng
Author-email: c.geng@esciencecenter.nl
License: Apache Software License 2.0
Keywords: fairdatapoint-client
Platform: UNKNOWN
Classifier: Development Status :: 2 - Pre-Alpha
Classifier: Intended Audience :: Developers
Classifier: Intended Audience :: Science/Research
Classifier: License :: OSI Approved :: Apache Software License
Classifier: Natural Language :: English
Classifier: Programming Language :: Python :: 3
Classifier: Programming Language :: Python :: 3.7
Classifier: Programming Language :: Python :: 3.8
Classifier: Programming Language :: Python :: 3.9
Requires-Dist: rdflib
Requires-Dist: rdflib-jsonld
Requires-Dist: requests
Provides-Extra: docs
Requires-Dist: Sphinx ; extra == 'docs'
Requires-Dist: ipython ; extra == 'docs'
Provides-Extra: tests
Requires-Dist: pytest ; extra == 'tests'
Requires-Dist: pytest-datadir-ng ; extra == 'tests'
Requires-Dist: pytest-cov ; extra == 'tests'
Requires-Dist: coveralls ; extra == 'tests'
Requires-Dist: requests-mock ; extra == 'tests'
